tayto/__init__.py
tayto/ci.py
tayto/execute.py
tayto/file.py
tayto/linux.py
tayto-0.1.5.dist-info/METADATA
tayto-0.1.5.dist-info/WHEEL
tayto-0.1.5.dist-info/licenses/LICENSE
tayto-0.1.5.dist-info/RECORD
