Metadata-Version: 2.1
Name: tayto
Version: 0.1.5
Summary: Tool for CI CD
Project-URL: Homepage, https://github.com/quangdaicaa/tayto
Project-URL: Bug Tracker, https://github.com/quangdaicaa/tayto
Author-email: quangdaicaa <quangnn@anninh.tv>
License-File: LICENSE
Classifier: License :: OSI Approved :: MIT License
Classifier: Operating System :: OS Independent
Classifier: Programming Language :: Python :: 3
Requires-Python: >=3.10
